README.md
setup.py
rasa_exp/__init__.py
rasa_exp.egg-info/PKG-INFO
rasa_exp.egg-info/SOURCES.txt
rasa_exp.egg-info/dependency_links.txt
rasa_exp.egg-info/requires.txt
rasa_exp.egg-info/top_level.txt
rasa_exp/core/__init__.py
rasa_exp/core/policies/__init__.py
rasa_exp/nlu/__init__.py
rasa_exp/nlu/classifiers/__init__.py
rasa_exp/nlu/debugger/__init__.py
rasa_exp/nlu/extractors/__init__.py
rasa_exp/nlu/extractors/regex_date_extractor.py
rasa_exp/nlu/featurizers/__init__.py
rasa_exp/nlu/tokenizers/__init__.py
rasa_exp/nlu/tokenizers/micro_addons_tokenizer.py
rasa_exp/nlu/tokenizers/simple_tokenizer.py
rasa_exp/nlu/utils/__init__.py
rasa_exp/utils/__init__.py