Metadata-Version: 1.0
Name: rasa-exp
Version: 0.0.3
Summary: rasa_exp
Home-page: https://github.com/shfshf/rasa_exp
Author: Hanfeng Song
Author-email: 1316478299@qq.com
License: Apache 2.0
Platform: UNKNOWN
